ork/__init__.py
ork/namegen.json
ork/namegen.py
ork/utils.py
ork-0.0.2.dist-info/LICENSE
ork-0.0.2.dist-info/METADATA
ork-0.0.2.dist-info/WHEEL
ork-0.0.2.dist-info/top_level.txt
ork-0.0.2.dist-info/RECORD
